less/__init__.py
less/cli/__init__.py
less/cli/cli.py
less.cli-0.1.3.dist-info/METADATA
less.cli-0.1.3.dist-info/WHEEL
less.cli-0.1.3.dist-info/entry_points.txt
less.cli-0.1.3.dist-info/top_level.txt
less.cli-0.1.3.dist-info/RECORD
