Metadata-Version: 2.1
Name: less.cli
Version: 0.1.3
Summary: Command line interface for less
Home-page: https://github.com/pashabitz/less.cli
Author: less
Author-email: pavelbitz@gmail.com
License: GPL3
Platform: UNKNOWN
Requires-Dist: requests
Requires-Dist: Click
